{
  "summary": "game_workspace:game_pipeline: Implement basic route cost calculation logic with unit tests.",
  "editable_files": [
    "game/routes.py",
    "tests/test_routes.py"
  ],
  "files_expected": [
    "game/routes.py",
    "tests/test_routes.py",
    "state/loop_snapshot.json",
    "state/website_notes.md",
    "state/memory.sqlite3",
    "site/index.html",
    "site/style.css"
  ],
  "website_change_reason": "Focus remains on core simulation logic before showcasing metrics.",
  "monetization_change_reason": "Maintain support placeholder until simulation demonstrates compelling core loop."
}
