{
  "loop_count": 15,
  "last_commit": "e85d42731ff0571eb16fe5005c14c6419baf25e6",
  "last_validation": {
    "success": true,
    "results": [
      {
        "success": true,
        "command": "/home/jishm/code/generations/.venv/bin/python3 -m pytest tests/test_journal.py tests/test_smoke.py",
        "output": ".....                                                                    [100%]\n5 passed in 159.79s (0:02:39)"
      }
    ]
  },
  "current_criteria_version": 1,
  "paused": false,
  "last_decision": "continue",
  "updated_at": "2026-03-06T10:18:10.222919+00:00"
}
