{
  "loop_count": 5,
  "last_commit": "4ffe50f0d8207a9267dc99eab409e84e164498d4",
  "last_validation": {
    "success": true,
    "results": [
      {
        "success": true,
        "command": "/usr/bin/python3 -m compileall src tests games",
        "output": "Listing 'src'...\nListing 'src/generations'...\nListing 'src/generations/adapters'...\nListing 'src/generations/journal'...\nListing 'src/generations/memory'...\nListing 'src/generations/web'...\nListing 'src/generations/web/static'...\nListing 'src/generations/web/templates'...\nListing 'tests'...\nListing 'games'...\nListing 'games/hello_game'..."
      }
    ]
  },
  "current_criteria_version": 1,
  "paused": false,
  "last_decision": "stop",
  "updated_at": "2026-03-05T21:21:01.099998+00:00"
}
